certbot_dns_netangels/__init__.py
certbot_dns_netangels/dns_netangels.py
certbot_dns_netangels-0.0.4.dist-info/LICENSE.txt
certbot_dns_netangels-0.0.4.dist-info/METADATA
certbot_dns_netangels-0.0.4.dist-info/WHEEL
certbot_dns_netangels-0.0.4.dist-info/entry_points.txt
certbot_dns_netangels-0.0.4.dist-info/top_level.txt
certbot_dns_netangels-0.0.4.dist-info/RECORD
